swajay_cv_toolkit/__init__.py
swajay_cv_toolkit/augmentations.py
swajay_cv_toolkit/losses.py
swajay_cv_toolkit/models.py
swajay_cv_toolkit/training.py
swajay_cv_toolkit/utils.py
swajay_cv_toolkit/version.py
swajay_cv_toolkit-1.0.9.dist-info/licenses/LICENSE
swajay_cv_toolkit-1.0.9.dist-info/METADATA
swajay_cv_toolkit-1.0.9.dist-info/WHEEL
swajay_cv_toolkit-1.0.9.dist-info/top_level.txt
swajay_cv_toolkit-1.0.9.dist-info/RECORD
