Metadata-Version: 2.4
Name: swajay-cv-toolkit
Version: 1.0.9
Summary: Advanced Computer Vision Toolkit for Image Classification
Home-page: https://github.com/swajayresources/swajay-cv-toolkit
Author: Swajay
Author-email: Swajay <swajaynandanwade04@gmail.com>
License: MIT
Project-URL: Homepage, https://github.com/swajayresources/swajay-cv-toolkit
Project-URL: Repository, https://github.com/swajayresources/swajay-cv-toolkit
Project-URL: Documentation, https://swajay-cv-toolkit.readthedocs.io/
Project-URL: Bug Tracker, https://github.com/swajayresources/swajay-cv-toolkit/issues
Keywords: computer-vision,deep-learning,image-classification,pytorch
Classifier: Development Status :: 4 - Beta
Classifier: Intended Audience :: Developers
Classifier: Intended Audience :: Science/Research
Classifier: License :: OSI Approved :: MIT License
Classifier: Operating System :: OS Independent
Classifier: Programming Language :: Python :: 3
Classifier: Programming Language :: Python :: 3.8
Classifier: Programming Language :: Python :: 3.9
Classifier: Programming Language :: Python :: 3.10
Classifier: Programming Language :: Python :: 3.11
Classifier: Topic :: Scientific/Engineering :: Artificial Intelligence
Classifier: Topic :: Scientific/Engineering :: Image Recognition
Requires-Python: >=3.8
License-File: LICENSE
Requires-Dist: torch>=1.12.0
Requires-Dist: torchvision>=0.13.0
Requires-Dist: timm>=0.6.0
Requires-Dist: albumentations>=1.3.0
Requires-Dist: opencv-python-headless>=4.6.0
Requires-Dist: numpy>=1.21.0
Requires-Dist: scikit-learn>=1.1.0
Requires-Dist: pandas>=1.4.0
Requires-Dist: Pillow>=8.3.0
Requires-Dist: tqdm>=4.64.0
Provides-Extra: dev
Requires-Dist: pytest>=6.0; extra == "dev"
Requires-Dist: pytest-cov>=2.0; extra == "dev"
Requires-Dist: black>=21.0; extra == "dev"
Requires-Dist: flake8>=3.8; extra == "dev"
Requires-Dist: mypy>=0.812; extra == "dev"
Provides-Extra: examples
Requires-Dist: matplotlib>=3.3.0; extra == "examples"
Requires-Dist: seaborn>=0.11.0; extra == "examples"
Requires-Dist: jupyter>=1.0.0; extra == "examples"
Provides-Extra: docs
Requires-Dist: sphinx>=4.0; extra == "docs"
Requires-Dist: sphinx-rtd-theme>=1.0; extra == "docs"
Requires-Dist: myst-parser>=0.17; extra == "docs"
Dynamic: author
Dynamic: home-page
Dynamic: license-file
Dynamic: requires-python
